energystats/__init__.py
energystats/decomposition/__init__.py
energystats/decomposition/dca.py
energystats/decomposition/ica.py
energystats/distributions/Dirichletdistobject.py
energystats/distributions/Exponentialdistobject.py
energystats/distributions/Normaldistobject.py
energystats/distributions/__init__.py
energystats/eda/__init__.py
energystats/eda/k_groups_clustering.py
energystats/eda/outlier_detection.py
energystats/tests/Bernoulli_test.py
energystats/tests/Geometric_tests.py
energystats/tests/Two_sample_test.py
energystats/tests/__init__.py
energystats/tests/btree.py
energystats/tests/cor.py
energystats/tests/disco_decomposition.py
energystats/tests/distribution_tests.py
energystats/tests/poisson_tests.py
energystats-0.5.2.dist-info/LICENSE
energystats-0.5.2.dist-info/METADATA
energystats-0.5.2.dist-info/WHEEL
energystats-0.5.2.dist-info/top_level.txt
energystats-0.5.2.dist-info/RECORD
